batteryclient/__init__.py
batteryclient/api_client.py
batteryclient/configuration.py
batteryclient/exceptions.py
batteryclient/model_utils.py
batteryclient/rest.py
batteryclient/api/__init__.py
batteryclient/api/users_api.py
batteryclient/apis/__init__.py
batteryclient/model/__init__.py
batteryclient/model/cell.py
batteryclient/model/column.py
batteryclient/model/dataset.py
batteryclient/model/equipment.py
batteryclient/model/error.py
batteryclient/model/range.py
batteryclient/model/user.py
batteryclient/models/__init__.py
batteryclient-1.0.2.dist-info/METADATA
batteryclient-1.0.2.dist-info/WHEEL
batteryclient-1.0.2.dist-info/top_level.txt
batteryclient-1.0.2.dist-info/RECORD
