Metadata-Version: 2.1
Name: batteryclient
Version: 1.0.2
Summary: Battery Data API
Home-page: 
Author: OpenAPI Generator community
Author-email: martin.robinson@cs.ox.ac.uk
License: Apache 2.0
Keywords: OpenAPI,OpenAPI-Generator,Battery Data API
Requires-Python: >=3.6
Requires-Dist: urllib3 (>=1.25.3)
Requires-Dist: python-dateutil
